hdlparse/__init__.py
hdlparse/__main__.py
hdlparse/minilexer.py
hdlparse/verilog_parser.py
hdlparse/vhdl_parser.py
hdltree/Analyzer.py
hdltree/Parser.py
hdltree/VhdlCstTransformer.py
hdltree/VhdlParseTreeTransformers.py
hdltree/__init__.py
hdltree/__main__.py
hdltree/cli.py
hdltree/symbol.py
hdltree/vhdl-2008.lark
hdltree-0.5.2.dist-info/licenses/LICENSE
nucanvas/__init__.py
nucanvas/cairo_backend.py
nucanvas/nucanvas.py
nucanvas/shapes.py
nucanvas/svg_backend.py
nucanvas/color/__init__.py
nucanvas/color/sinebow.py
symbolator/__init__.py
symbolator/__main__.py
symbolator/symbolator.py
symbolator_sphinx/LICENSE.Sphinx
symbolator_sphinx/__init__.py
symbolator_sphinx/symbolator_sphinx.py
hdltree-0.5.2.dist-info/METADATA
hdltree-0.5.2.dist-info/WHEEL
hdltree-0.5.2.dist-info/entry_points.txt
hdltree-0.5.2.dist-info/top_level.txt
hdltree-0.5.2.dist-info/RECORD
