Metadata-Version: 2.4
Name: hdltree
Version: 0.5.2
Summary: Pure Python HDL parser, plus symbol generator and sphinx domain
Author-email: Rajan Patel <rpatel3001@gmail.com>
License: Copyright © 2025 Rajan Patel
Project-URL: source, https://github.com/rpatel3001/hdltree
Keywords: RTL,HDL,VHDL,System,Verilog,SystemVerilog,symbol,symbolator,sphinx,hdlparse,parse,format,validate
Classifier: Development Status :: 3 - Alpha
Classifier: Environment :: Console
Classifier: Operating System :: OS Independent
Classifier: Intended Audience :: Developers
Classifier: Topic :: Multimedia :: Graphics
Classifier: Topic :: Software Development :: Documentation
Classifier: Topic :: Software Development :: Code Generators
Classifier: Topic :: Documentation
Classifier: Topic :: Documentation :: Sphinx
Classifier: Natural Language :: English
Classifier: Programming Language :: Python :: 3
Classifier: License :: OSI Approved :: MIT License
Requires-Python: >=3.10
License-File: LICENSE
Requires-Dist: lark>=1.0.0
Requires-Dist: lark-ambig-tools>=1.0.0
Requires-Dist: rich>=13.0.0
Requires-Dist: pydot>=3.0.0
Provides-Extra: regex
Requires-Dist: regex; extra == "regex"
Provides-Extra: symbolator
Requires-Dist: pygobject; extra == "symbolator"
Requires-Dist: pycairo; extra == "symbolator"
Dynamic: license-file
